Workbook

Sheet RawData
A1: Year | B1: Revenue | C1: COGS | D1: OperatingExpenses | E1: InterestExpense | F1: Taxes | G1: NetIncome
A2: 2005 | B2: 1919092000 | C2: 775381000 | D2: 574072000 | E2: 68000000 | F2: 267625000 | G2: =B2 - C2 - D2 - E2 - F2 -> 234014000
A3: 2006 | B3: 1578456000 | C3: 655154000 | D3: 394131000 | E3: 388000 | F3: 168786000 | G3: =B3 - C3 - D3 - E3 - F3 -> 359997000
A4: 2007 | B4: 3205498000 | C4: 1283148000 | D4: 861756000 | E4: 122000000 | F4: 154017000 | G4: =B4 - C4 - D4 - E4 - F4 -> 784577000
A5: 2008 | B5: 2689700000 | C5: 1048728000 | D5: 709641000 | E5: 21000 | F5: 306150000 | G5: =B5 - C5 - D5 - E5 - F5 -> 625160000
A6: 2009 | B6: 2456000000 | C6: 989032000 | D6: 651596000 | E6: 177000 | F6: 255100000 | G6: =B6 - C6 - D6 - E6 - F6 -> 560095000
A7: 2010 | B7: 2253800000 | C7: 904119000 | D7: 606982000 | E7: 8000 | F7: 218327000 | G7: =B7 - C7 - D7 - E7 - F7 -> 524364000
A8: 2011 | B8: 4826686000 | C8: 1955824000 | D8: 1430128000 | E8: 171000 | F8: 401578000 | G8: =B8 - C8 - D8 - E8 - F8 -> 1038985000
A9: 2012 | B9: 4231400000 | C9: 1662579000 | D9: 1250979000 | E9: 446000 | F9: 402281000 | G9: =B9 - C9 - D9 - E9 - F9 -> 915115000
A10: 2013 | B10: 3872000000 | C10: 1560255000 | D10: 1207130000 | E10: 244000 | F10: 316625000 | G10: =B10 - C10 - D10 - E10 - F10 -> 787746000
A11: 2014 | B11: 3664000000 | C11: 1470426000 | D11: 972365000 | E11: 342000 | F11: 349775000 | G11: =B11 - C11 - D11 - E11 - F11 -> 871092000
A12: 2015 | B12: 5700950000 | C12: 2190005000 | D12: 1650740000 | E12: 88447000 | F12: 452905000 | G12: =B12 - C12 - D12 - E12 - F12 -> 1318853000
A13: 2016 | B13: 5541400000 | C13: 2173390000 | D13: 1720445000 | E13: 90996000 | F13: 378844000 | G13: =B13 - C13 - D13 - E13 - F13 -> 1177725000
... A22: 2025 | B22: 6820000000 | C22: 2467000000 | D22: 1988000000 | E22: 136000000 | F22: 594000000 | G22: =B22 - C22 - D22 - E22 - F22 -> 1635000000

Sheet Model
A1: Year | B1: Revenue | C1: COGS | D1: OperatingExpenses | E1: InterestExpense | F1: Taxes | G1: NetIncome
A2: 2005 | B2: 1919092000 | C2: 775381000 | D2: 574072000 | E2: 68000000 | F2: 267625000 | G2: =B2 - C2 - D2 - E2 - F2 -> 234014000
A3: 2006 | B3: 1578456000 | C3: 655154000 | D3: 394131000 | E3: 388000 | F3: 168786000 | G3: =B3 - C3 - D3 - E3 - F3 -> 359997000
A4: 2007 | B4: 3205498000 | C4: 1283148000 | D4: 861756000 | E4: 122000000 | F4: 154017000 | G4: =B4 - C4 - D4 - E4 - F4 -> 784577000
A5: 2008 | B5: 2689700000 | C5: 1048728000 | D5: 709641000 | E5: 21000 | F5: 306150000 | G5: =B5 - C5 - D5 - E5 - F5 -> 625160000
A6: 2009 | B6: 2456000000 | C6: 989032000 | D6: 651596000 | E6: 177000 | F6: 255100000 | G6: =B6 - C6 - D6 - E6 - F6 -> 560095000
A7: 2010 | B7: 2253800000 | C7: 904119000 | D7: 606982000 | E7: 8000 | F7: 218327000 | G7: =B7 - C7 - D7 - E7 - F7 -> 524364000
A8: 2011 | B8: 4826686000 | C8: 1955824000 | D8: 1430128000 | E8: 171000 | F8: 401578000 | G8: =B8 - C8 - D8 - E8 - F8 -> 1038985000
A9: 2012 | B9: 4231400000 | C9: 1662579000 | D9: 1250979000 | E9: 446000 | F9: 402281000 | G9: =B9 - C9 - D9 - E9 - F9 -> 915115000
A10: 2013 | B10: 3872000000 | C10: 1560255000 | D10: 1207130000 | E10: 244000 | F10: 316625000 | G10: =B10 - C10 - D10 - E10 - F10 -> 787746000
A11: 2014 | B11: 3664000000 | C11: 1470426000 | D11: 972365000 | E11: 342000 | F11: 349775000 | G11: =B11 - C11 - D11 - E11 - F11 -> 871092000
A12: 2015 | B12: 5700950000 | C12: 2190005000 | D12: 1650740000 | E12: 88447000 | F12: 452905000 | G12: =B12 - C12 - D12 - E12 - F12 -> 1318853000
A13: 2016 | B13: 5541400000 | C13: 2173390000 | D13: 1720445000 | E13: 90996000 | F13: 378844000 | G13: =B13 - C13 - D13 - E13 - F13 -> 1177725000
... A22: 2025 | B22: 6820000000 | C22: 2467000000 | D22: 1988000000 | E22: 136000000 | F22: 594000000 | G22: =B22 - C22 - D22 - E22 - F22 -> 1635000000
A23: 2026 | B23: =B22*(1+Assumptions!$B$2) -> 7.843e+09 | C23: =B23*Assumptions!$B$3 -> 4.7058e+09 | D23: =B23*Assumptions!$B$4 -> 1.17645e+09 | E23: =Assumptions!$B$5 -> 1.6133333e+08 | F23: =(B23-C23-D23-E23)*Assumptions!$B$6 -> 4.4985417e+08 | G23: =B23 - C23 - D23 - E23 - F23 -> 1.3495625e+09
A24: 2027 | B24: =B23*(1+Assumptions!$B$2) -> 9.01945e+09 | C24: =B24*Assumptions!$B$3 -> 5.41167e+09 | D24: =B24*Assumptions!$B$4 -> 1.3529175e+09 | E24: =Assumptions!$B$5 -> 1.6133333e+08 | F24: =(B24-C24-D24-E24)*Assumptions!$B$6 -> 5.2338229e+08 | G24: =B24 - C24 - D24 - E24 - F24 -> 1.5701469e+09
A25: 2028 | B25: =B24*(1+Assumptions!$B$2) -> 1.0372367e+10 | C25: =B25*Assumptions!$B$3 -> 6.2234205e+09 | D25: =B25*Assumptions!$B$4 -> 1.5558551e+09 | E25: =Assumptions!$B$5 -> 1.6133333e+08 | F25: =(B25-C25-D25-E25)*Assumptions!$B$6 -> 6.0793964e+08 | G25: =B25 - C25 - D25 - E25 - F25 -> 1.8238189e+09

Sheet Line Chart for Revenue Forec

Sheet Bar Chart for Expense Breakd
A6: Year | B6: COGS | C6: OperatingExpenses | D6: Revenue
A7: 2020 | B7: 2226000000 | C7: 1645000000 | D7: 5945000000
A8: 2021 | B8: 2108000000 | C8: 1541000000 | D8: 5523000000
A9: 2022 | B9: 2102000000 | C9: 1523000000 | D9: 5509000000
A10: 2023 | B10: 2946000000 | C10: 2512000000 | D10: 8440000000
A11: 2024 | B11: 2552000000 | C11: 2187000000 | D11: 7286000000
A12: 2025 | B12: 2467000000 | C12: 1988000000 | D12: 6820000000
A13: 2026 | B13: =D13*Assumptions!$B$3 -> 4.7058e+09 | C13: =D13*Assumptions!$B$4 -> 1.17645e+09 | D13: =D12*(1+Assumptions!$B$2) -> 7.843e+09
A14: 2027 | B14: =D14*Assumptions!$B$3 -> 5.41167e+09 | C14: =D14*Assumptions!$B$4 -> 1.3529175e+09 | D14: =D13*(1+Assumptions!$B$2) -> 9.01945e+09
A15: 2028 | B15: =D15*Assumptions!$B$3 -> 6.2234205e+09 | C15: =D15*Assumptions!$B$4 -> 1.5558551e+09 | D15: =D14*(1+Assumptions!$B$2) -> 1.0372367e+10

Sheet Assumptions
A1: Assumption
A2: Revenue Growth % | B2: 0.15
A3: COGS % of Revenue | B3: 0.6
A4: OpEx % of Revenue | B4: 0.15
A5: Interest | B5: =(176000000 + 172000000 + 136000000) / 3 -> 1.6133333e+08
A6: Tax Rate | B6: 0.25

Sheet Outputs
D2: Revenue Growth % | E2: =Assumptions!$B$2 -> 0.15
D3: COGS % of Revenue | E3: =Assumptions!$B$3 -> 0.6
D4: Net Income | E4: =Model!G23 -> 1.3495625e+09 | J4: What-If Analysis
G9: COGS%
G10: 0.5 | H10: 0.55 | I10: 0.6
E11: Revenue Growth % | F11: 0.05 | G11: 1758762500 | H11: 1.490225e+09 | I11: 1221687500 | J11: Net Income
F12: 0.1 | G12: 1.848275e+09 | H12: 1566950000 | I12: 1.285625e+09
F13: 0.15 | G13: 1937787500 | H13: 1.643675e+09 | I13: 1.3495625e+09
H17: Goal Seek
C18: To Achieve | D18: Net Income | E18: 4000000
C19: Required | D19: Revenue | E19: 1.1258966e+11
L21: Scenario Manager
D27: Revenue Growth % | E27: $E$26
D28: COGS % of Revenue | E28: $E$27 | F28: Scenario Summary
D29: OpEx % of Revenue | E29: $E$28 | H29: Current Values: | I29: Best Case | J29: Most Likely | K29: Worst Case
F31: Changing Cells:
G32: $E$26 | I32: 0.15 | J32: 0.1 | K32: 0.05
G33: $E$27 | I33: 0.5 | J33: 0.55 | K33: 0.6
G34: $E$28 | I34: 0.1 | J34: 0.15 | K34: 0.2
F35: Result Cells:
G36: $E$4 | H36: 1349562500 | I36: 1349562500 | J36: 1349562500 | K36: 1349562500
F37: Notes: Current Values column represents values of changing cells at
F38: time Scenario Summary Report was created. Changing cells for each
F39: scenario are highlighted in gray.
